gtempco2.py
gtempco2-0.0.9.dist-info/METADATA
gtempco2-0.0.9.dist-info/WHEEL
gtempco2-0.0.9.dist-info/entry_points.txt
gtempco2-0.0.9.dist-info/top_level.txt
gtempco2-0.0.9.dist-info/RECORD
