Metadata-Version: 2.1
Name: gtempco2
Version: 0.0.9
Summary: A package for displaying global temperature and co2
Home-page: https://github.com/y-takefuji/gtempco2
Author: yoshiyasu takefuji
Author-email: takefuji@keio.jp
License: UNKNOWN
Project-URL: Bug Tracker, https://github.com/y-takefuji/gtempco2
Platform: UNKNOWN
Classifier: Programming Language :: Python :: 3
Classifier: License :: OSI Approved :: MIT License
Classifier: Operating System :: OS Independent
Requires-Python: >=3.8
